MANIFEST.in
README.md
setup.py
stackFifoLifo/StackFifo.py
stackFifoLifo/StackLifo.py
stackFifoLifo/__init__.py
stackFifoLifo.egg-info/PKG-INFO
stackFifoLifo.egg-info/SOURCES.txt
stackFifoLifo.egg-info/dependency_links.txt
stackFifoLifo.egg-info/top_level.txt