Metadata-Version: 1.1
Name: stackFifoLifo
Version: 0.0.1
Summary: Stack FIFO and LIFO
Home-page: http://github.com/oryxr/stackFifoLifo
Author: Pierre Lucas
Author-email: pierre.lucas@altie.fr
License: GPL
Platform: UNKNOWN
Classifier: Operating System :: OS Independent
Classifier: Programming Language :: Python :: 3.5
Classifier: Topic :: Communications
